{
  "users": [
    {
      "id": 1,
      "name": "Tampan",
      "email": "tomposon@gmail.com",
      "age": 23,
      "city": "Bantul, Yogyakarta",
      "cart": [
        {
          "goods": "Xiaomi 1A",
          "total": 4
        }
      ]
    },
    {
      "id": 2,
      "name": "Tes",
      "email": "tomposon@gmail.com",
      "age": 23,
      "city": "Bantul, Yogyakarta",
      "cart": [
        {
          "goods": "Xiaomi 1A",
          "total": 4
        }
      ]
    },
    {
      "id": 3,
      "name": "Namaku",
      "email": "tomposon@gmail.com",
      "age": 23,
      "city": "Bantul, Yogyakarta",
      "cart": [
        {
          "goods": "Xiaomi 1A",
          "total": 4
        }
      ]
    },
    {
      "id": 4,
      "name": "Sherina",
      "email": "tomposon@gmail.com",
      "age": 23,
      "city": "Bantul, Yogyakarta",
      "cart": [
        {
          "goods": "Xiaomi 1A",
          "total": 4
        }
      ]
    },
    {
      "id": 5,
      "name": "Panji",
      "email": "tomposon@gmail.com",
      "age": 23,
      "city": "Bantul, Yogyakarta",
      "cart": [
        {
          "goods": "Xiaomi 1A",
          "total": 4
        }
      ]
    },
    {
      "id": 6,
      "name": "Kocak",
      "email": "tomposon@gmail.com",
      "age": 23,
      "city": "Bantul, Yogyakarta",
      "cart": [
        {
          "goods": "Xiaomi 1A",
          "total": 4
        }
      ]
    },
    {
      "id": 7,
      "name": "Harimau",
      "email": "tomposon@gmail.com",
      "age": 23,
      "city": "Bantul, Yogyakarta",
      "cart": [
        {
          "goods": "Xiaomi 1A",
          "total": 4
        }
      ]
    },
    {
      "id": 8,
      "name": "Kocheng",
      "email": "tomposon@gmail.com",
      "age": 23,
      "city": "Bantul, Yogyakarta",
      "cart": [
        {
          "goods": "Xiaomi 1A",
          "total": 4
        }
      ]
    },
    {
      "id": 9,
      "name": "Abdul",
      "email": "tomposon@gmail.com",
      "age": 23,
      "city": "Bantul, Yogyakarta",
      "cart": [
        {
          "goods": "Xiaomi 1A",
          "total": 4
        }
      ]
    },
    {
      "id": 10,
      "name": "Pahero",
      "email": "tomposon@gmail.com",
      "age": 23,
      "city": "Bantul, Yogyakarta",
      "cart": [
        {
          "goods": "Xiaomi 1A",
          "total": 4
        }
      ]
    },
    {
      "id": 11,
      "name": "Nisa",
      "email": "tomposon@gmail.com",
      "age": 23,
      "city": "Bantul, Yogyakarta",
      "cart": [
        {
          "goods": "Xiaomi 1A",
          "total": 4
        }
      ]
    },
    {
      "id": 12,
      "name": "Mantul",
      "email": "tomposon@gmail.com",
      "age": 23,
      "city": "Bantul, Yogyakarta",
      "cart": [
        {
          "goods": "Xiaomi 1A",
          "total": 4
        }
      ]
    }
  ]
}